dpapick3/__init__.py
dpapick3/blob.py
dpapick3/credhist.py
dpapick3/crypto.py
dpapick3/eater.py
dpapick3/masterkey.py
dpapick3/probe.py
dpapick3/registry.py
dpapick3/probes/__init__.py
dpapick3/probes/certificate.py
dpapick3-0.7.1.dist-info/licenses/LICENSE
dpapick3-0.7.1.dist-info/METADATA
dpapick3-0.7.1.dist-info/WHEEL
dpapick3-0.7.1.dist-info/top_level.txt
dpapick3-0.7.1.dist-info/RECORD
